appkit_assistant/configuration.py
appkit_assistant/pages.py
appkit_assistant/backend/model_manager.py
appkit_assistant/backend/schemas.py
appkit_assistant/backend/system_prompt_cache.py
appkit_assistant/backend/database/models.py
appkit_assistant/backend/database/repositories.py
appkit_assistant/backend/models/__init__.py
appkit_assistant/backend/models/anthropic.py
appkit_assistant/backend/models/google.py
appkit_assistant/backend/models/openai.py
appkit_assistant/backend/models/perplexity.py
appkit_assistant/backend/processors/__init__.py
appkit_assistant/backend/processors/claude_responses_processor.py
appkit_assistant/backend/processors/gemini_responses_processor.py
appkit_assistant/backend/processors/lorem_ipsum_processor.py
appkit_assistant/backend/processors/mcp_mixin.py
appkit_assistant/backend/processors/openai_base.py
appkit_assistant/backend/processors/openai_chat_completion_processor.py
appkit_assistant/backend/processors/openai_responses_processor.py
appkit_assistant/backend/processors/perplexity_processor.py
appkit_assistant/backend/processors/processor_base.py
appkit_assistant/backend/processors/streaming_base.py
appkit_assistant/backend/services/auth_error_detector.py
appkit_assistant/backend/services/chunk_factory.py
appkit_assistant/backend/services/citation_handler.py
appkit_assistant/backend/services/file_cleanup_service.py
appkit_assistant/backend/services/file_manager.py
appkit_assistant/backend/services/file_upload_service.py
appkit_assistant/backend/services/file_validation.py
appkit_assistant/backend/services/mcp_auth_service.py
appkit_assistant/backend/services/mcp_token_service.py
appkit_assistant/backend/services/message_converter.py
appkit_assistant/backend/services/openai_client_service.py
appkit_assistant/backend/services/response_accumulator.py
appkit_assistant/backend/services/system_prompt_builder.py
appkit_assistant/backend/services/thread_service.py
appkit_assistant/components/__init__.py
appkit_assistant/components/composer.py
appkit_assistant-1.0.1.dist-info/METADATA
appkit_assistant-1.0.1.dist-info/WHEEL
appkit_assistant-1.0.1.dist-info/RECORD
