Metadata-Version: 2.4
Name: appkit-assistant
Version: 1.0.1
Summary: Add your description here
Project-URL: Homepage, https://github.com/jenreh/appkit
Project-URL: Documentation, https://github.com/jenreh/appkit/tree/main/docs
Project-URL: Repository, https://github.com/jenreh/appkit
Project-URL: Issues, https://github.com/jenreh/appkit/issues
Author: Jens Rehpöhler
License: MIT
Keywords: components,mantine,reflex,ui,web
Classifier: Intended Audience :: Developers
Classifier: License :: OSI Approved :: MIT License
Classifier: Programming Language :: Python :: 3
Classifier: Programming Language :: Python :: 3.13
Classifier: Topic :: Software Development :: Libraries :: Python Modules
Classifier: Topic :: Software Development :: User Interfaces
Requires-Python: >=3.13
Requires-Dist: anthropic>=0.77.0
Requires-Dist: appkit-commons
Requires-Dist: appkit-mantine
Requires-Dist: appkit-ui
Requires-Dist: apscheduler>=3.11.2
Requires-Dist: google-genai>=1.60.0
Requires-Dist: mcp>=1.26.0
Requires-Dist: openai>=2.16.0
Requires-Dist: python-multipart>=0.0.22
Requires-Dist: reflex>=0.8.26
